{"kind":"identitytoolkit#DownloadAccountResponse","users":[{"localId":"t8BwFVGszrbbC4WfiwPM0IOQH0zJ","createdAt":"1727176055621","lastLoginAt":"1727339742104","displayName":"vitaliyshaban","photoUrl":"","passwordHash":"fakeHash:salt=fakeSalt2QhNfaZ0cVxBJudzwnOz:password=123456","salt":"fakeSalt2QhNfaZ0cVxBJudzwnOz","passwordUpdatedAt":1727423830300,"providerUserInfo":[{"providerId":"password","email":"vitaliyshaban@gmail.com","federatedId":"vitaliyshaban@gmail.com","rawId":"vitaliyshaban@gmail.com","displayName":"vitaliyshaban","photoUrl":""}],"validSince":"1727423830","email":"vitaliyshaban@gmail.com","emailVerified":false,"disabled":false}]}